AUTHORS.rst
CONTRIBUTING.rst
HISTORY.rst
LICENSE
MANIFEST.in
README.rst
setup.cfg
setup.py
docs/Makefile
docs/authors.rst
docs/conf.py
docs/contributing.rst
docs/history.rst
docs/index.rst
docs/installation.rst
docs/make.bat
docs/readme.rst
docs/usage.rst
op_env/__init__.py
op_env/_cli.py
op_env/op.py
op_env/op_env.py
op_env.egg-info/PKG-INFO
op_env.egg-info/SOURCES.txt
op_env.egg-info/dependency_links.txt
op_env.egg-info/entry_points.txt
op_env.egg-info/not-zip-safe
op_env.egg-info/requires.txt
op_env.egg-info/top_level.txt
tests/__init__.py
tests/conftest.py
tests/test_op_env.py