Metadata-Version: 2.1
Name: op-env
Version: 0.6.0
Summary: op-env allows you to use 1Password entries as environment variable-style secrets
Home-page: https://github.com/apiology/op_env
Author: Vince Broz
Author-email: vince@broz.cc
License: MIT license
Keywords: op_env
Platform: UNKNOWN
Classifier: Development Status :: 2 - Pre-Alpha
Classifier: Intended Audience :: Developers
Classifier: License :: OSI Approved :: MIT License
Classifier: Natural Language :: English
Classifier: Programming Language :: Python :: 3
Classifier: Programming Language :: Python :: 3.6
Classifier: Programming Language :: Python :: 3.7
Classifier: Programming Language :: Python :: 3.8
Classifier: Programming Language :: Python :: 3.9
Requires-Python: >=3.6
